mypackage_wsc/__init__.py
mypackage_wsc/generate.py
mypackage_wsc/infra_bootstrap.py
mypackage_wsc/infra_builder_terraform.py
mypackage_wsc/install_nginx.py
mypackage_wsc/remove_terraform.py
mypackage_wsc-1.0.0.dist-info/LICENSE
mypackage_wsc-1.0.0.dist-info/METADATA
mypackage_wsc-1.0.0.dist-info/WHEEL
mypackage_wsc-1.0.0.dist-info/top_level.txt
mypackage_wsc-1.0.0.dist-info/RECORD
