Metadata-Version: 2.1
Name: mypackage-wsc
Version: 1.0.0
Summary: wedeployer package version beta
Home-page: https://github.com/mehdi-wsc/mypackage.git
Author: mehdi wsc
Author-email: kerbedjm@gmail.com
License: UNKNOWN
Platform: UNKNOWN
Classifier: Programming Language :: Python :: 3
Classifier: License :: OSI Approved :: GNU General Public License v3 (GPLv3)
Classifier: Operating System :: OS Independent
Requires-Python: >=3.6
